franklab_nwb_extensions/__init__.py
franklab_nwb_extensions/core.py
franklab_nwb_extensions/create_franklab_spec.py
franklab_nwb_extensions/fl_extension.py
franklab_nwb_extensions/franklab.extensions.yaml
franklab_nwb_extensions/franklab.namespace.yaml
franklab_nwb_extensions-0.1.4.dev0.dist-info/LICENSE
franklab_nwb_extensions-0.1.4.dev0.dist-info/METADATA
franklab_nwb_extensions-0.1.4.dev0.dist-info/WHEEL
franklab_nwb_extensions-0.1.4.dev0.dist-info/entry_points.txt
franklab_nwb_extensions-0.1.4.dev0.dist-info/top_level.txt
franklab_nwb_extensions-0.1.4.dev0.dist-info/RECORD
