Metadata-Version: 2.1
Name: franklab-nwb-extensions
Version: 0.1.4.dev0
Summary: Frank lab nwb specific extensions
Home-page: https://github.com/LorenFrankLab/franklab_nwb_extensions
Author: Frank Lab members
Author-email: loren@phy.ucsf.edu
License: UNKNOWN
Platform: UNKNOWN
Classifier: Programming Language :: Python :: 3
Classifier: License :: OSI Approved :: MIT License
Classifier: Operating System :: OS Independent
Requires-Python: >=3.6
Requires-Dist: pynwb
Requires-Dist: hdmf
